{
  "project_info": {
    "project_number": "286181637242",
    "project_id": "water-reminder-app-896d7",
    "storage_bucket": "water-reminder-app-896d7.appspot.com"
  },
  "client": [
    {
      "client_info": {
        "mobilesdk_app_id": "1:286181637242:android:9e78b1d100cafecfd04fc3",
        "android_client_info": {
          "package_name": "uz.gita.waterreminder"
        }
      },
      "oauth_client": [
        {
          "client_id": "286181637242-ne8mh5ctnso1fubaktt9m29hijct7ggf.apps.googleusercontent.com",
          "client_type": 3
        }
      ],
      "api_key": [
        {
          "current_key": "AIzaSyAHHAoosJtwr9G7k6B02pldfAtPv0EkuOw"
        }
      ],
      "services": {
        "appinvite_service": {
          "other_platform_oauth_client": [
            {
              "client_id": "286181637242-ne8mh5ctnso1fubaktt9m29hijct7ggf.apps.googleusercontent.com",
              "client_type": 3
            }
          ]
        }
      }
    }
  ],
  "configuration_version": "1"
}